panelyze/__init__.py
panelyze/core.py
panelyze-0.2.0.dist-info/licenses/LICENSE
panelyze-0.2.0.dist-info/METADATA
panelyze-0.2.0.dist-info/WHEEL
panelyze-0.2.0.dist-info/top_level.txt
panelyze-0.2.0.dist-info/RECORD
