Metadata-Version: 2.4
Name: panelyze
Version: 0.2.0
Summary: An interactive, spreadsheet-style DataFrame viewer for Jupyter
Home-page: https://github.com/yourusername/panelyze
Author: Saeed Raad
Author-email: s.ghiasirad@outlook.com
License: MIT
Project-URL: Bug Tracker, https://github.com/yourusername/panelyze/issues
Project-URL: Source Code, https://github.com/saeedraad/panelyze
Classifier: Programming Language :: Python :: 3
Classifier: Operating System :: OS Independent
Requires-Python: >=3.8
License-File: LICENSE
Requires-Dist: pandas
Requires-Dist: ipywidgets
Requires-Dist: itables
Dynamic: license-file
